<annotation>
  <folder>VOC2007</folder>
  <filename>image.005637.jpg</filename>
  <source>
    <database>The VOC2007 Database</database>
    <annotation>PASCAL VOC2007</annotation>
    <image>flickr</image>
    <flickrid>0</flickrid>
  </source>
  <owner>
    <flickrid>Group 27</flickrid>
    <name>?</name>
  </owner>
  <size>
    <width>600</width>
    <height>450</height>
    <depth>3</depth>
  </size>
  <segmented>0</segmented>
  <object>
    <name>traffic_sign</name>
    <pose>Unspecified</pose>
    <truncated>0</truncated>
    <difficult>0</difficult>
    <bnbbox>
      <xmin>397.1130221130221</xmin>
      <ymin>65.87257281553399</ymin>
      <xmax>427.2199017199017</xmax>
      <ymax>91.48543689320388</ymax>
    </bnbbox>
  </object>
</annotation>
