<annotation>
  <folder>VOC2007</folder>
  <filename>image.003895.jpg</filename>
  <source>
    <database>The VOC2007 Database</database>
    <annotation>PASCAL VOC2007</annotation>
    <image>flickr</image>
    <flickrid>0</flickrid>
  </source>
  <owner>
    <flickrid>Group 27</flickrid>
    <name>?</name>
  </owner>
  <size>
    <width>600</width>
    <height>450</height>
    <depth>3</depth>
  </size>
  <segmented>0</segmented>
  <object>
    <name>traffic_sign</name>
    <pose>Unspecified</pose>
    <truncated>0</truncated>
    <difficult>0</difficult>
    <bnbbox>
      <xmin>410.44348894348894</xmin>
      <ymin>112.35800970873787</ymin>
      <xmax>432.8439803439804</xmax>
      <ymax>144.52063106796118</ymax>
    </bnbbox>
  </object>
</annotation>
