<annotation>
  <folder>VOC2007</folder>
  <filename>image.004835.jpg</filename>
  <source>
    <database>The VOC2007 Database</database>
    <annotation>PASCAL VOC2007</annotation>
    <image>flickr</image>
    <flickrid>0</flickrid>
  </source>
  <owner>
    <flickrid>Group 27</flickrid>
    <name>?</name>
  </owner>
  <size>
    <width>600</width>
    <height>450</height>
    <depth>3</depth>
  </size>
  <segmented>0</segmented>
  <object>
    <name>traffic_sign</name>
    <pose>Unspecified</pose>
    <truncated>0</truncated>
    <difficult>0</difficult>
    <bnbbox>
      <xmin>11.163390663390663</xmin>
      <ymin>66.04733009708738</ymin>
      <xmax>36.530712530712535</xmax>
      <ymax>104.16990291262137</ymax>
    </bnbbox>
  </object>
</annotation>
