<annotation>
  <folder>VOC2007</folder>
  <filename>image.002844.jpg</filename>
  <source>
    <database>The VOC2007 Database</database>
    <annotation>PASCAL VOC2007</annotation>
    <image>flickr</image>
    <flickrid>0</flickrid>
  </source>
  <owner>
    <flickrid>Group 27</flickrid>
    <name>?</name>
  </owner>
  <size>
    <width>600</width>
    <height>450</height>
    <depth>3</depth>
  </size>
  <segmented>0</segmented>
  <object>
    <name>traffic_sign</name>
    <pose>Unspecified</pose>
    <truncated>0</truncated>
    <difficult>0</difficult>
    <bnbbox>
      <xmin>155.9041769041769</xmin>
      <ymin>46.314320388349515</ymin>
      <xmax>176.48034398034397</xmax>
      <ymax>87.73907766990291</ymax>
    </bnbbox>
  </object>
</annotation>
