<annotation>
  <folder>VOC2007</folder>
  <filename>image.004417.jpg</filename>
  <source>
    <database>The VOC2007 Database</database>
    <annotation>PASCAL VOC2007</annotation>
    <image>flickr</image>
    <flickrid>0</flickrid>
  </source>
  <owner>
    <flickrid>Group 27</flickrid>
    <name>?</name>
  </owner>
  <size>
    <width>600</width>
    <height>450</height>
    <depth>3</depth>
  </size>
  <segmented>0</segmented>
  <object>
    <name>traffic_sign</name>
    <pose>Unspecified</pose>
    <truncated>0</truncated>
    <difficult>0</difficult>
    <bnbbox>
      <xmin>79.43366093366093</xmin>
      <ymin>38.15169902912621</ymin>
      <xmax>181.85012285012286</xmax>
      <ymax>145.07402912621362</ymax>
    </bnbbox>
  </object>
</annotation>
