<annotation>
  <folder>VOC2007</folder>
  <filename>image.002260.jpg</filename>
  <source>
    <database>The VOC2007 Database</database>
    <annotation>PASCAL VOC2007</annotation>
    <image>flickr</image>
    <flickrid>0</flickrid>
  </source>
  <owner>
    <flickrid>Group 27</flickrid>
    <name>?</name>
  </owner>
  <size>
    <width>600</width>
    <height>450</height>
    <depth>3</depth>
  </size>
  <segmented>0</segmented>
  <object>
    <name>traffic_sign</name>
    <pose>Unspecified</pose>
    <truncated>0</truncated>
    <difficult>0</difficult>
    <bnbbox>
      <xmin>30.57493857493857</xmin>
      <ymin>315.3604368932039</ymin>
      <xmax>86.27395577395578</xmax>
      <ymax>363.81189320388347</ymax>
    </bnbbox>
  </object>
</annotation>
